oauth_magento/__init__.py
oauth_magento/oauth_magento_openedx.py
magento_oauth-0.2.4.dist-info/METADATA
magento_oauth-0.2.4.dist-info/WHEEL
magento_oauth-0.2.4.dist-info/top_level.txt
magento_oauth-0.2.4.dist-info/RECORD
