Metadata-Version: 2.1
Name: magento-oauth
Version: 0.2.4
Summary: A Python package for Magento OAuth2 authentication
Home-page: https://github.com/Francisco-Huerta/oauth_magento_openedx
Author: Francisco Huerta Yumha
Author-email: UNKNOWN
License: UNKNOWN
Platform: UNKNOWN
Classifier: Development Status :: 3 - Alpha
Classifier: License :: OSI Approved :: MIT License
Classifier: Programming Language :: Python
Classifier: Programming Language :: Python :: Implementation :: CPython
Classifier: Programming Language :: Python :: Implementation :: PyPy
Classifier: Topic :: Internet :: WWW/HTTP
Classifier: Topic :: Software Development :: Libraries :: Python Modules
Requires-Dist: requests (<3.0,>=2.25)
Requires-Dist: social-auth-core (<5.0,>=4.0)
